LICENSE
MANIFEST.in
README.md
pyspark_sugar.py
setup.py
pyspark_sugar.egg-info/PKG-INFO
pyspark_sugar.egg-info/SOURCES.txt
pyspark_sugar.egg-info/dependency_links.txt
pyspark_sugar.egg-info/requires.txt
pyspark_sugar.egg-info/top_level.txt