Metadata-Version: 1.0
Name: pyspark-sugar
Version: 0.4
Summary: SparkUI enchancements with pyspark
Home-page: https://github.com/sashgorokhov/pyspark-sugar
Author: sashgorokhov
Author-email: sashgorokhov@gmail.com
License: MIT
Keywords: pyspark
Platform: UNKNOWN
